{
  "code": 2000,
  "codename": "Koyuki",
  "data": {
    "max_page": 537,
    "type_num": {
      "AlliedOperation": 12,
      "BigRaid": 83,
      "ContentImprovements": 393,
      "Double": 872,
      "Event": 486,
      "Gacha": 763,
      "Live": 77,
      "MainStory": 120,
      "Maintenance": 422,
      "MiniBattle": 188,
      "Other": 677,
      "OtherStory": 59,
      "OutsideGames": 816,
      "Raid": 242,
      "Trivia": 29,
      "WebEvent": 129
    },
    "timeline": [
      {
        "id": 3205,
        "line_type": "Globle",
        "title": "国际服活动「After-School Sweets Story: Sweet Secrets and Shootouts」常驻化",
        "image": "https://static.kivo.wiki/images/timeline/WPj7hjYBdI22xINxCz0ZsRh5A8LjWOlm.jpg",
        "body_summary": "[Immortalized Event Notice] The Event Story 'After-School Sweets Story: Sweet Secrets and Shootouts'",
        "type": "Event",
        "url": "x.com/EN_BlueArchive/status/1843531501260156975",
        "start_time": 1728381600,
        "end_time": 1728381600
      },
      {
        "id": 3204,
        "line_type": "Globle",
        "title": "国际服活动「Balancing Schale's Books with the General Student Council」#7",
        "image": "https://static.kivo.wiki/images/timeline/5mkSC0adRPpHMJB9O98FHrH0PlOiYpDh.jpg",
        "body_summary": "[Mini Event Notice] Balancing Schale's Books with the General Student Council is back! Earn enhancem",
        "type": "Event",
        "url": "x.com/EN_BlueArchive/status/1843528400549621859",
        "start_time": 1728381600,
        "end_time": 1729562400
      },
      {
        "id": 3162,
        "line_type": "Globle",
        "title": "国际服卡池复刻「A devout holy, and candy-like day.」 #3",
        "image": "https://static.kivo.wiki/images/timeline/Kcin8S8pQb1qHjQx37gbTa26jfHZD2sJ.jpg",
        "body_summary": "[Rerun Pick-Up Recruitment Preview] A Rerun Pick-Up Recruitment will begin on 10/8 (Tue)! 💌Pick-Up S",
        "type": "Gacha",
        "url": "x.com/EN_BlueArchive/status/1842104871899791584",
        "start_time": 1728381600,
        "end_time": 1728957600
      },
      {
        "id": 3161,
        "line_type": "Globle",
        "title": "国际服卡池复刻「She's here! It's her! Our superstar, Reisa is here!」",
        "image": "https://static.kivo.wiki/images/timeline/PPNtyTeyhPz2tvvFilYyfMOxoYcDRMgw.jpg",
        "body_summary": "[Rerun Pick-Up Recruitment Preview] A Rerun Pick-Up Recruitment will begin on 10/8 (Tue)! 💌Pick-Up S",
        "type": "Gacha",
        "url": "x.com/EN_BlueArchive/status/1842101095079837950",
        "start_time": 1728381600,
        "end_time": 1728957600
      },
      {
        "id": 3160,
        "line_type": "Globle",
        "title": "国际服卡池复刻「It's important I get this out there: I dont't like cats.」 #2",
        "image": "https://static.kivo.wiki/images/timeline/w6qoDM5WKUfPvvteCAHfSwyPnV4qkZlR.jpg",
        "body_summary": "[Rerun Pick-Up Recruitment Preview] A Rerun Pick-Up Recruitment will begin on 10/8 (Tue)! 💌Pick-Up S",
        "type": "Gacha",
        "url": "x.com/EN_BlueArchive/status/1842097328041206090",
        "start_time": 1728381600,
        "end_time": 1728957600
      },
      {
        "id": 3159,
        "line_type": "Globle",
        "title": "国际服主线Vol.1 第三章 Part1更新",
        "image": "https://static.kivo.wiki/images/timeline/AzNVg4d8KeiB6Iktplh9dAbTf7gBUOwp.jpg",
        "body_summary": "[Main Story Announcement] The Main Story Vol. 1 Foreclosure Task Force Chapter 3 Part 1 'Traces of a",
        "type": "MainStory",
        "url": "x.com/EN_BlueArchive/status/1842082227749802106",
        "start_time": 1728381600,
        "end_time": 1728381600
      },
      {
        "id": 3206,
        "line_type": "Globle",
        "title": "国际服违规账号封禁 #35",
        "image": "",
        "body_summary": "[10/8 (Tue) Ban Notice] We have taken disciplinary actions against the players who were abusing in-g",
        "type": "Other",
        "url": "x.com/EN_BlueArchive/status/1843547846450278721",
        "start_time": 1728370980,
        "end_time": 1728370980
      },
      {
        "id": 3203,
        "line_type": "Globle",
        "title": "国际服主线Vol.1 第三章Part 1 PV公开",
        "image": "",
        "body_summary": "Main Story Update Notice Main Story Vol. 1: Foreclosure Task Force Chapter 3, Part 1: 'Traces of a D",
        "type": "OutsideGames",
        "url": "x.com/EN_BlueArchive/status/1843524083407040949",
        "start_time": 1728365340,
        "end_time": 1728365340
      },
      {
        "id": 3163,
        "line_type": "Globle",
        "title": "国际服例行维护 #70",
        "image": "",
        "body_summary": "[10/8 Scheduled Maintenance Notice] Sensei, there is a scheduled maintenance on 10/8 (Tue). 🗓️Mainte",
        "type": "Maintenance",
        "url": "x.com/EN_BlueArchive/status/1842127519064961310",
        "start_time": 1728352800,
        "end_time": 1728367200
      },
      {
        "id": 3158,
        "line_type": "Globle",
        "title": "国际服联合火力演习 #26",
        "image": "https://static.kivo.wiki/images/timeline/3B3HH1JM88uq1gjXo9FKkMyMlYm9e8q8.jpg",
        "body_summary": "[Joint Firing Drill Preview] The Joint Firing Drill (Breakthrough Drill) will start on 10/8 (Tue)! ➡",
        "type": "MiniBattle",
        "url": "x.com/EN_BlueArchive/status/1841372548388495451",
        "start_time": 1728327611,
        "end_time": 1728932411
      }
    ]
  },
  "message": "OK",
  "success": true,
  "time": 1780428855,
  "version": "1.0.0-beta.43"
}
