{
  "code": 2000,
  "codename": "Koyuki",
  "data": {
    "max_page": 539,
    "type_num": {
      "AlliedOperation": 12,
      "BigRaid": 83,
      "ContentImprovements": 393,
      "Double": 873,
      "Event": 487,
      "Gacha": 767,
      "Live": 79,
      "MainStory": 120,
      "Maintenance": 423,
      "MiniBattle": 189,
      "Other": 677,
      "OtherStory": 59,
      "OutsideGames": 824,
      "Raid": 242,
      "Trivia": 29,
      "WebEvent": 129
    },
    "timeline": [
      {
        "id": 1916,
        "line_type": "JP",
        "title": "卡池复刻「逃げ水を夢に見て」＆「徒桜を拾い集めて」",
        "image": "https://static.kivo.wiki/images/timeline/Ku2vF0i2xL3KFkWeAWwZeSBkNpLBijnl.jpg",
        "body_summary": "【ピックアップ募集・予告】 まもなく、復刻ピックアップ募集「逃げ水を夢に見て」＆「徒桜を拾い集めて」が開催されます！ 詳細については、下記URLよりご確認ください！ 🔹ピックアップ生徒 ★3 ミサキ(",
        "type": "Gacha",
        "url": "twitter.com/Blue_ArchiveJP/status/1747121611126501875",
        "start_time": 1705482059,
        "end_time": 1706061659
      },
      {
        "id": 1842,
        "line_type": "JP",
        "title": "大决战：市街地戦・シロ＆クロ1",
        "image": "https://static.kivo.wiki/images/timeline/RYYqOeeetUlvybhZ2vpW1clz3PuskSug.jpg",
        "body_summary": "【新情報 ⑧】 つきましては大決戦と総力戦の情報になります。 総力戦「ホバークラフト」と大決戦「シロ＆クロ」の開催が決定しました！ それぞれの開催期間と詳細情報はこちらの画像にてご確認ください。 #ブ",
        "type": "BigRaid",
        "url": "twitter.com/Blue_ArchiveJP/status/1738886601072423340",
        "start_time": 1705460400,
        "end_time": 1706039999
      },
      {
        "id": 1917,
        "line_type": "JP",
        "title": "炸服31",
        "image": "",
        "body_summary": "【臨時メンテナンス】 ただいま、臨時メンテナンスを実施しております。 メンテナンス中はゲームをご利用いただくことができませんので、ご注意ください。 終了時間は17:00前後を予定しております。 ▼詳細",
        "type": "Maintenance",
        "url": "twitter.com/Blue_ArchiveJP/status/1747438719840436296",
        "start_time": 1705456829,
        "end_time": 1705482029
      },
      {
        "id": 5087,
        "line_type": "JP",
        "title": "任务Normal2倍#33",
        "image": "https://static.kivo.wiki/images/timeline/8GAoWj5P5cPOVIOzKiFhBV1np3mwMOfg.jpg",
        "body_summary": "【キャンペーン予告】 1/17(水)より「任務(Normal)」での報酬ドロップ量が2倍になるキャンペーンを開催します！ ▼開催期間 1/17(水)4:00 〜 1/21(日)3:59 この機会に、生",
        "type": "Double",
        "url": "x.com/Blue_ArchiveJP/status/1747091853428887653",
        "start_time": 1705435200,
        "end_time": 1705780799
      },
      {
        "id": 1893,
        "line_type": "Globle",
        "title": "国际服卡池复刻「The children's innocent smile. I will Protect!」2",
        "image": "https://static.kivo.wiki/images/timeline/eELcw1EFmuRSVoqwyPNtnO1Orf05orXu.jpg",
        "body_summary": "[Rerun Pick-Up Recruitment Preview] A Rerun Pick-Up Recruitment will begin on 1/16 (Tue)! Pick-Up St",
        "type": "Gacha",
        "url": "twitter.com/EN_BlueArchive/status/1745687062446235732",
        "start_time": 1705370458,
        "end_time": 1705975198
      },
      {
        "id": 1896,
        "line_type": "Globle",
        "title": "国际服活动常驻化「Playing Tag at Neverland」",
        "image": "https://static.kivo.wiki/images/timeline/s5lcBRNhlZtDR0eAZupQbc72FYbkAlc3.jpg",
        "body_summary": "[Immortalized Event Notice] The Event Story, Playing Tag at Neverland, will be immortalized starting",
        "type": "Event",
        "url": "twitter.com/EN_BlueArchive/status/1745702151165505877",
        "start_time": 1705370444,
        "end_time": 1705370444
      },
      {
        "id": 1894,
        "line_type": "Globle",
        "title": "国际服卡池复刻「Welcome Sensei, to My secret lab!」2",
        "image": "https://static.kivo.wiki/images/timeline/qRUhaDfAGLa4KNV8bil5cxEkt8LeABjI.jpg",
        "body_summary": "[Rerun Pick-Up Recruitment Preview] A Rerun Pick-Up Recruitment will begin on 1/16 (Tue)! Pick-Up St",
        "type": "Gacha",
        "url": "twitter.com/EN_BlueArchive/status/1745690822886994162",
        "start_time": 1705370443,
        "end_time": 1705975183
      },
      {
        "id": 1895,
        "line_type": "Globle",
        "title": "国际服卡池复刻「P—Please don't call me kokona without my title! I'm not just some little kid, you know?!」",
        "image": "https://static.kivo.wiki/images/timeline/VjS9xaH453RrN7jZLgAIzGQ1XBWBBMOi.jpg",
        "body_summary": "[Rerun Pick-Up Recruitment Preview] A Rerun Pick-Up Recruitment will begin on 1/16 (Tue)! Pick-Up St",
        "type": "Gacha",
        "url": "twitter.com/EN_BlueArchive/status/1745694598792679685",
        "start_time": 1705370440,
        "end_time": 1705975180
      },
      {
        "id": 1898,
        "line_type": "Globle",
        "title": "国际服大决战BETA KAITEN FX Mk.0 (Urban)",
        "image": "https://static.kivo.wiki/images/timeline/YlB1DnCUHk2A9uAuhRdvVuQyU1Y1xayD.jpg",
        "body_summary": "[Grand Assault Open Notice] The Grand Assault - KAITEN FX Mk.0 (Urban Warfare) has opened 1/16 (Tue)",
        "type": "BigRaid",
        "url": "twitter.com/EN_BlueArchive/status/1747154215493927060",
        "start_time": 1705370426,
        "end_time": 1705949966
      },
      {
        "id": 1897,
        "line_type": "Globle",
        "title": "国际服特别依赖2倍23",
        "image": "https://static.kivo.wiki/images/timeline/AZGgIlLpt7RvbmyPZKmF41OgdtCXeJTy.jpg",
        "body_summary": "[Double Drop Campaign Preview] Starting 1/15 (Mon), Commissions rewards will be doubled! Don't miss ",
        "type": "Double",
        "url": "twitter.com/EN_BlueArchive/status/1746064553320886504",
        "start_time": 1705345251,
        "end_time": 1705949991
      }
    ]
  },
  "message": "OK",
  "success": true,
  "time": 1780781717,
  "version": "1.0.0-beta.43"
}
