{
  "code": 2000,
  "codename": "Koyuki",
  "data": {
    "id": 889,
    "name": "CH0280_home",
    "remark": "",
    "type": "home",
    "skel_file": "https://static.kivo.wiki/spines/CH0280_home/CH0280_home.skel",
    "atlas_file": "https://static.kivo.wiki/spines/CH0280_home/CH0280_home.atlas",
    "images": [
      "https://static.kivo.wiki/spines/CH0280_home/CH0280_home_2.png",
      "https://static.kivo.wiki/spines/CH0280_home/CH0280_home.png"
    ]
  },
  "message": "OK",
  "success": true,
  "time": 1781383851,
  "version": "1.0.0-beta.43"
}
