{
  "code": 2000,
  "codename": "Koyuki",
  "data": {
    "id": 942,
    "name": "ToSchool_JTFMobSwimsuit1",
    "remark": "泳装站姿",
    "type": "spr",
    "skel_file": "https://static.kivo.wiki/spines/ToSchool_JTFMobSwimsuit1/swimsuit1.skel",
    "atlas_file": "https://static.kivo.wiki/spines/ToSchool_JTFMobSwimsuit1/swimsuit1.atlas",
    "images": [
      "https://static.kivo.wiki/spines/ToSchool_JTFMobSwimsuit1/swimsuit1.png"
    ]
  },
  "message": "OK",
  "success": true,
  "time": 1780693342,
  "version": "1.0.0-beta.43"
}
