{
  "code": 2000,
  "codename": "Koyuki",
  "data": {
    "id": 121,
    "name": "角色设计师（外包&外聘）",
    "name_cn": "",
    "image": "https://static.kivo.wiki/images/relation/SCgXkw8qZF8nXdd8EKuPJ770EaL3RXOz.png",
    "description": "# 角色设计师（外包&外聘）\n在最终章制作人员名单中属于Cooperated Illustrators的角色设计师们。\n许多设计师同时担任了原画一职，但有以下成员仅负责了设计，未负责原画：\n- ミモザ\n- Vinoker\n- 春夏冬ゆう\n- sabet\n- 桧野ひなこ\n- maruchi\n- 二色こぺ\n- Crab D\n- 本田ロアロ\n- Owa",
    "filter_whitelist": [],
    "main_students": [
      {
        "id": 419,
        "skin": "",
        "family_name": "",
        "given_name": "キキ",
        "avatar": "https://static.kivo.wiki/images/students/%20%E3%82%AD%E3%82%AD/original/avatar.png"
      },
      {
        "id": 420,
        "skin": "",
        "family_name": "",
        "given_name": "NAMYO",
        "avatar": "https://static.kivo.wiki/images/students/%20NAMYO/original/avatar.png"
      },
      {
        "id": 421,
        "skin": "",
        "family_name": "",
        "given_name": "mona",
        "avatar": "https://static.kivo.wiki/images/students/%20mona/original/avatar.png"
      },
      {
        "id": 422,
        "skin": "",
        "family_name": "",
        "given_name": "OSUK2",
        "avatar": "https://static.kivo.wiki/images/students/%20OSUK2/original/avatar.png"
      },
      {
        "id": 423,
        "skin": "",
        "family_name": "",
        "given_name": "ぶくろて",
        "avatar": "https://static.kivo.wiki/images/students/%20%E3%81%B6%E3%81%8F%E3%82%8D%E3%81%A6/original/avatar.png"
      },
      {
        "id": 424,
        "skin": "",
        "family_name": "",
        "given_name": "nemoga",
        "avatar": "https://static.kivo.wiki/images/students/%20nemoga/original/avatar.png"
      },
      {
        "id": 426,
        "skin": "",
        "family_name": "",
        "given_name": "seicoh",
        "avatar": "https://static.kivo.wiki/images/students/%20seicoh/original/avatar.png"
      },
      {
        "id": 428,
        "skin": "",
        "family_name": "",
        "given_name": "まきあっと",
        "avatar": "https://static.kivo.wiki/images/students/%20%E3%81%BE%E3%81%8D%E3%81%82%E3%81%A3%E3%81%A8/original/avatar.png"
      },
      {
        "id": 429,
        "skin": "",
        "family_name": "",
        "given_name": "イコモチ",
        "avatar": "https://static.kivo.wiki/images/students/%20%E3%82%A4%E3%82%B3%E3%83%A2%E3%83%81/original/avatar.png"
      },
      {
        "id": 430,
        "skin": "",
        "family_name": "",
        "given_name": "tokki",
        "avatar": "https://static.kivo.wiki/images/students/%20tokki/original/avatar.png"
      },
      {
        "id": 432,
        "skin": "",
        "family_name": "",
        "given_name": "Fame",
        "avatar": "https://static.kivo.wiki/images/students/%20Fame/original/avatar.png"
      },
      {
        "id": 433,
        "skin": "",
        "family_name": "",
        "given_name": "tonito",
        "avatar": "https://static.kivo.wiki/images/students/%20tonito/original/avatar.png"
      },
      {
        "id": 435,
        "skin": "",
        "family_name": "",
        "given_name": "にぎりうさぎ",
        "avatar": "https://static.kivo.wiki/images/students/%20%E3%81%AB%E3%81%8E%E3%82%8A%E3%81%86%E3%81%95%E3%81%8E/original/avatar.png"
      },
      {
        "id": 437,
        "skin": "",
        "family_name": "",
        "given_name": "はねこと",
        "avatar": "https://static.kivo.wiki/images/students/%20%E3%81%AF%E3%81%AD%E3%81%93%E3%81%A8/original/avatar.png"
      },
      {
        "id": 439,
        "skin": "",
        "family_name": "",
        "given_name": "ミミトケ",
        "avatar": "https://static.kivo.wiki/images/students/%20%E3%83%9F%E3%83%9F%E3%83%88%E3%82%B1/original/avatar.png"
      },
      {
        "id": 440,
        "skin": "",
        "family_name": "",
        "given_name": "ポップキュン",
        "avatar": "https://static.kivo.wiki/images/students/%20%E3%83%9D%E3%83%83%E3%83%97%E3%82%AD%E3%83%A5%E3%83%B3/original/avatar.png"
      },
      {
        "id": 441,
        "skin": "",
        "family_name": "",
        "given_name": "ヌードル",
        "avatar": "https://static.kivo.wiki/images/students/%20%E3%83%8C%E3%83%BC%E3%83%89%E3%83%AB/original/avatar.png"
      },
      {
        "id": 442,
        "skin": "",
        "family_name": "",
        "given_name": "日下雲",
        "avatar": "https://static.kivo.wiki/images/students/%20%E6%97%A5%E4%B8%8B%E9%9B%B2/original/avatar.png"
      },
      {
        "id": 443,
        "skin": "",
        "family_name": "",
        "given_name": "eno",
        "avatar": "https://static.kivo.wiki/images/students/%20eno/original/avatar.png"
      },
      {
        "id": 444,
        "skin": "",
        "family_name": "",
        "given_name": "カンザリン",
        "avatar": "https://static.kivo.wiki/images/students/%20%E3%82%AB%E3%83%B3%E3%82%B6%E3%83%AA%E3%83%B3/original/avatar.png"
      },
      {
        "id": 446,
        "skin": "",
        "family_name": "",
        "given_name": "ビョルチ",
        "avatar": "https://static.kivo.wiki/images/students/%20%E3%83%93%E3%83%A7%E3%83%AB%E3%83%81/original/avatar.png"
      },
      {
        "id": 447,
        "skin": "",
        "family_name": "",
        "given_name": "Empew",
        "avatar": "https://static.kivo.wiki/images/students/%20Empew/original/avatar.png"
      },
      {
        "id": 448,
        "skin": "",
        "family_name": "",
        "given_name": "やまかわ",
        "avatar": "https://static.kivo.wiki/images/students/%20%E3%82%84%E3%81%BE%E3%81%8B%E3%82%8F/original/avatar.png"
      },
      {
        "id": 449,
        "skin": "",
        "family_name": "",
        "given_name": "nino",
        "avatar": "https://static.kivo.wiki/images/students/%20nino/original/avatar.png"
      },
      {
        "id": 450,
        "skin": "",
        "family_name": "",
        "given_name": "あやみ",
        "avatar": "https://static.kivo.wiki/images/students/%20%E3%81%82%E3%82%84%E3%81%BF/original/avatar.png"
      },
      {
        "id": 451,
        "skin": "",
        "family_name": "",
        "given_name": "三脚たこ",
        "avatar": "https://static.kivo.wiki/images/students/%20%E4%B8%89%E8%84%9A%E3%81%9F%E3%81%93/original/avatar.png"
      },
      {
        "id": 452,
        "skin": "",
        "family_name": "",
        "given_name": "ni02",
        "avatar": "https://static.kivo.wiki/images/students/%20ni02/original/avatar.png"
      },
      {
        "id": 455,
        "skin": "",
        "family_name": "",
        "given_name": "RONOPU",
        "avatar": "https://static.kivo.wiki/images/students/%20RONOPU/original/avatar.png"
      },
      {
        "id": 456,
        "skin": "",
        "family_name": "",
        "given_name": "mery",
        "avatar": "https://static.kivo.wiki/images/students/%20mery/original/avatar.png"
      },
      {
        "id": 458,
        "skin": "",
        "family_name": "",
        "given_name": "ミモザ",
        "avatar": "https://static.kivo.wiki/images/students/%20%E3%83%9F%E3%83%A2%E3%82%B6/original/avatar.png"
      },
      {
        "id": 459,
        "skin": "",
        "family_name": "",
        "given_name": "Vinoker",
        "avatar": "https://static.kivo.wiki/images/students/%20Vinoker/original/avatar.png"
      },
      {
        "id": 460,
        "skin": "",
        "family_name": "",
        "given_name": "春夏冬ゆう",
        "avatar": "https://static.kivo.wiki/images/students/%20%E6%98%A5%E5%A4%8F%E5%86%AC%E3%82%86%E3%81%86/original/avatar.png"
      },
      {
        "id": 461,
        "skin": "",
        "family_name": "",
        "given_name": "sabet",
        "avatar": "https://static.kivo.wiki/images/students/%20sabet/original/avatar.png"
      },
      {
        "id": 462,
        "skin": "",
        "family_name": "",
        "given_name": "桧野ひなこ",
        "avatar": "https://static.kivo.wiki/images/students/%20%E6%A1%A7%E9%87%8E%E3%81%B2%E3%81%AA%E3%81%93/original/avatar.png"
      },
      {
        "id": 463,
        "skin": "",
        "family_name": "",
        "given_name": "maruchi",
        "avatar": "https://static.kivo.wiki/images/students/%20maruchi/original/avatar.png"
      },
      {
        "id": 464,
        "skin": "",
        "family_name": "",
        "given_name": "二色こぺ",
        "avatar": "https://static.kivo.wiki/images/students/%20%E4%BA%8C%E8%89%B2%E3%81%93%E3%81%BA/original/avatar.png"
      },
      {
        "id": 465,
        "skin": "",
        "family_name": "",
        "given_name": "Crab D",
        "avatar": "https://static.kivo.wiki/images/students/%20Crab%20D/original/avatar.png"
      },
      {
        "id": 466,
        "skin": "",
        "family_name": "",
        "given_name": "本田ロアロ",
        "avatar": "https://static.kivo.wiki/images/students/%20%E6%9C%AC%E7%94%B0%E3%83%AD%E3%82%A2%E3%83%AD/original/avatar.png"
      },
      {
        "id": 540,
        "skin": "",
        "family_name": "",
        "given_name": "BILLBUNG",
        "avatar": "https://static.kivo.wiki/images/students/%20BILLBUNG/original/avatar.png"
      }
    ],
    "secondary_students": null
  },
  "message": "OK",
  "success": true,
  "time": 1780615857,
  "version": "1.0.0-beta.43"
}
