{
  "code": 2000,
  "codename": "Koyuki",
  "data": {
    "max_page": 191,
    "item": [
      {
        "id": 1100,
        "name": "议长准备的最高级巧克力喷泉",
        "type": "default",
        "icon": "https://static.kivo.wiki/images/item/icon/4gBVapCpsCnESyy0QzE81jrkDCz1AhyR.png",
        "rarity": 1,
        "description": "真琴特别为老师准备了和派对一起准备的最高级的巧克力喷泉。即使这也是个很棒的东西，但是因为是根据想要制作的更完美的东西而改造的，所以偶尔马达会失控，向四面八方喷射巧克力，所以使用时需要注意。"
      },
      {
        "id": 285,
        "name": "印有格赫娜校徽的补给箱",
        "type": "default",
        "icon": "https://static.kivo.wiki/images/item/icon/E3urCWUWMWNqvM2ZX0thZpqpzBHkKBtK.png",
        "rarity": 1,
        "description": "风纪委员会为了迎接夏季合宿训练亲自准备的补给箱。 里面装著有助于训练的物品。没有空箱，可以放心使用。"
      },
      {
        "id": 1414,
        "name": "应用射击练习册",
        "type": "default",
        "icon": "https://static.kivo.wiki/images/item/icon/BBfOV6HDNXxaH47UkgVCvYFj7Md3O0Mv.png",
        "rarity": 3,
        "description": "用于学生的能力解放而发行的教材。"
      },
      {
        "id": 1413,
        "name": "应用体育练习册",
        "type": "default",
        "icon": "https://static.kivo.wiki/images/item/icon/fKMUjCvCRC3qg1GO3w9rbifCRXHyDKXz.png",
        "rarity": 3,
        "description": "用于学生的能力解放而发行的教材。"
      },
      {
        "id": 1415,
        "name": "应用卫生练习册",
        "type": "default",
        "icon": "https://static.kivo.wiki/images/item/icon/0NI6TBy6mOAxdnBrft3jiq1O0D14EMuE.png",
        "rarity": 3,
        "description": "用于学生的能力解放而发行的教材。"
      },
      {
        "id": 259,
        "name": "樱花糯米糕",
        "type": "default",
        "icon": "https://static.kivo.wiki/images/item/icon/lwJFRWJx6Ek07MR0gU5UdVaC5tgCnmNX.png",
        "rarity": 1,
        "description": "百鬼夜行的传统茶室百夜堂的畅销甜点。柔软浓厚的香甜确实无敌。"
      },
      {
        "id": 30,
        "name": "樱花巧克力",
        "type": "default",
        "icon": "https://static.kivo.wiki/images/item/icon/vNvrVyHuHE9ZK5QyJ7AEainHS95ThkxS.png",
        "rarity": 1,
        "description": "弥守所准备的樱花形手工巧克力。即使不会读心术，吃上一口想必也能感受到她的心意吧。"
      },
      {
        "id": 125,
        "name": "勇士的巧克力（道具）",
        "type": "default",
        "icon": "https://static.kivo.wiki/images/item/icon/KDdB4Y6zrwLeXj6NQBCBLCSIXLjQ1RoG.png",
        "rarity": 1,
        "description": "柚子和老师一起玩的RPG游戏中赠送的期间限定巧克力道具。服用后可以稍微恢复玩家的体力。"
      },
      {
        "id": 1813,
        "name": "游乐园门票",
        "type": "default",
        "icon": "https://static.kivo.wiki/images/item/icon/26rqMN8iDafCFojv9mP5jskfr67IFQxe.png",
        "rarity": 1,
        "description": "游乐园的入场票券。没有它就无法入园——这是理所当然的事。"
      },
      {
        "id": 467,
        "name": "游戏开发部系列家具抽选箱",
        "type": "default",
        "icon": "https://static.kivo.wiki/images/item/icon/EQkuUz35iHWdeMm8dyEbQY5hQHr0Zaj4.png",
        "rarity": 4,
        "description": "使用时以相同的概率获得1个游戏开发部系列家具的抽选箱。"
      }
    ]
  },
  "message": "OK",
  "success": true,
  "time": 1780950504,
  "version": "1.0.0-beta.43"
}
