{
  "code": 2000,
  "codename": "Koyuki",
  "data": {
    "id": 1243,
    "line_type": "Globle",
    "title": "国际服更新「Expert Permit」",
    "summary": "[Expert Permit Shop Update Notice] You can get the Expert Permits added in the 11/8 update as Daily ",
    "image": "https://static.kivo.wiki/images/timeline/mcacMZaS5SR36DVe5is8brmWirhYBcHp.jpg",
    "body": "[Expert Permit Shop Update Notice]\n\nYou can get the Expert Permits added in the 11/8 update as Daily and Weekly Task Rewards or by using AP at Max Lv. \nThen trade Expert Permits for valuable growth currencies like Special Pick-Up students' Elephs in the shop!\n\n#BlueArchive![ocKhWCPj09DKezAEkJPL7mHsypFbL43y.jpg](https://kivo.wiki/files/1348/ocKhWCPj09DKezAEkJPL7mHsypFbL43y.jpg)",
    "type": "ContentImprovements",
    "url": "twitter.com/EN_BlueArchive/status/1590630346021904384",
    "start_time": 1667898051,
    "end_time": 1667898051,
    "created_at": 1701720004,
    "updated_at": 1715575519
  },
  "message": "OK",
  "success": true,
  "time": 1780617426,
  "version": "1.0.0-beta.43"
}
