{
  "code": 2000,
  "codename": "Koyuki",
  "data": {
    "id": 1288,
    "line_type": "Globle",
    "title": "国际服特别依赖2倍11",
    "summary": "[Double Drop Campaign Preview] Starting 1/2 (Mon), Commissions rewards will be doubled! Don't miss o",
    "image": "https://static.kivo.wiki/images/timeline/RHuI0BnyJAgnYRA44IJnYC53DN8qJPDU.jpg",
    "body": "[Double Drop Campaign Preview]\n\nStarting 1/2 (Mon), Commissions rewards will be doubled! \nDon't miss out this chance to get Activity Reports and Credit Points!\n\n🗓️Period: 1/2 (Mon) 19:00 – 1/9 (Mon) 18:59 (UTC)\n\n#BlueArchive![nWMhtZfVhiR2ph1kPgYaWVZZTpCKJPbv.jpg](https://kivo.wiki/files/1348/nWMhtZfVhiR2ph1kPgYaWVZZTpCKJPbv.jpg)",
    "type": "Double",
    "url": "twitter.com/EN_BlueArchive/status/1609444438463463426",
    "start_time": 1672686040,
    "end_time": 1673290780,
    "created_at": 1701745677,
    "updated_at": 1715575520
  },
  "message": "OK",
  "success": true,
  "time": 1780617402,
  "version": "1.0.0-beta.43"
}
