{
  "code": 2000,
  "codename": "Koyuki",
  "data": {
    "id": 1962,
    "line_type": "CN",
    "title": "银镜伊织（泳装）",
    "summary": "//////////档案启封////////// ■银镜伊织（泳装） 歌赫娜风纪委员会所属的冷酷专家，正在参加夏季集训。 和其他风纪委员一起监控着歌赫娜的问题儿童，以防她们在海滩闹事。虽然表面上不露声",
    "image": "https://static.kivo.wiki/images/timeline/0SEcDyXeS5kHjWMi5DEkNrKCHjKHtVes.jpg",
    "body": "//////////档案启封////////// \n\n■银镜伊织（泳装）\n\n\n\n歌赫娜风纪委员会所属的冷酷专家，正在参加夏季集训。\n\n和其他风纪委员一起监控着歌赫娜的问题儿童，以防她们在海滩闹事。虽然表面上不露声色，但内心对难得的夏日集训被一群笨蛋问题儿童搞砸这件事感到相当不满。\n\n\n\n“我，我可不是在偷懒。我正在执行侦察任务，你可别误会啊。”\n\n![1YjAL3r5rOoThKpUgF1TevHncYyyTrmR.jpg](https://kivo.wiki/files/1348/1YjAL3r5rOoThKpUgF1TevHncYyyTrmR.jpg)",
    "type": "Other",
    "url": "www.bilibili.com/opus/870844210276728947",
    "start_time": 1701614195,
    "end_time": 1701614196,
    "created_at": 1706279881,
    "updated_at": 1715575523
  },
  "message": "OK",
  "success": true,
  "time": 1780617181,
  "version": "1.0.0-beta.43"
}
