{
  "code": 2000,
  "codename": "Koyuki",
  "data": {
    "id": 2273,
    "line_type": "Globle",
    "title": "国际服活动复刻「On Your Mark @ Millennium Kivotos Halo Festival」",
    "summary": "[Event Update Notice] The \"On Your Mark @ Millennium Kivotos Halo Festival\" Event Story is back! 🗓️P",
    "image": "https://static.kivo.wiki/images/timeline/apdn963KJcyFQ1pVKkuEznHW8FubUFDN.jpg",
    "body": "[Event Update Notice]\n\nThe \"On Your Mark @ Millennium Kivotos Halo Festival\" Event Story is back!\n\n🗓️Period: 3/12 (Tue) After Maintenance – 3/21 (Thu) 1:59 AM (UTC)\n\n#BlueArchive![sUp17lAJeZ68kSCE98FaoLM3qWK0w8BL.jpg](https://kivo.wiki/files/1348/sUp17lAJeZ68kSCE98FaoLM3qWK0w8BL.jpg)",
    "type": "Event",
    "url": "twitter.com/EN_BlueArchive/status/1767454317395718431",
    "start_time": 1710226809,
    "end_time": 1710986349,
    "created_at": 1710299981,
    "updated_at": 1715575524
  },
  "message": "OK",
  "success": true,
  "time": 1780617086,
  "version": "1.0.0-beta.43"
}
