{
  "code": 2000,
  "codename": "Koyuki",
  "data": {
    "id": 2738,
    "line_type": "CN",
    "title": "活动【夏日的问候！阿洛娜的特别签到奖励！】",
    "summary": "【夏日的问候！阿洛娜的特别签到奖励！】即将开始，活动期间累计登录游戏，即可获得青辉石×1200和海滩游泳圈（3★家具）！老师可千万不要错过啦！ ■ 活动时间 06月13日 维护结束后 ~ 07月18日",
    "image": "https://static.kivo.wiki/images/timeline/4creeZAO6v9vr3gVSpJJCEXGB7tdT2Ep.jpg",
    "body": "【夏日的问候！阿洛娜的特别签到奖励！】即将开始，活动期间累计登录游戏，即可获得青辉石×1200和海滩游泳圈（3★家具）！老师可千万不要错过啦！\n\n■ 活动时间\n06月13日 维护结束后 ~ 07月18日 03:59\n\n■ 奖励内容\n累计登录1天：青辉石 × 200\n累计登录2天：青辉石 × 200\n累计登录3天：青辉石 × 200\n累计登录4天：青辉石 × 200\n累计登录5天：青辉石 × 200\n累计登录6天：青辉石 × 200\n累计登录7天：海滩游泳圈 × 1\n\n■ 注意事项\n• 【海滩游泳圈（3★家具）】可以布置在咖啡厅内并提升舒适度。\n• 【海滩游泳圈（3★家具）】目前仅可通过此签到活动获得。\n![8kGi6o8dRVWoRmZqqGcxiK32gHpCf0FZ.jpg](https://kivo.wiki/files/1348/8kGi6o8dRVWoRmZqqGcxiK32gHpCf0FZ.jpg)",
    "type": "Event",
    "url": "weibo.com/6011443154/OibQ68M0I",
    "start_time": 1718258440,
    "end_time": 1721246440,
    "created_at": 1719729527,
    "updated_at": 1719729527
  },
  "message": "OK",
  "success": true,
  "time": 1780616988,
  "version": "1.0.0-beta.43"
}
