{
  "code": 2000,
  "codename": "Koyuki",
  "data": {
    "id": 2786,
    "line_type": "Globle",
    "title": "国际服卡池复刻「Starting now, I will exercise my authority as the winner! No, you can't refuse! Heehee~」2",
    "summary": "[Unique Rerun Pick-Up Recruitment Preview] A Unique Rerun Pick-Up Recruitment will begin on 7/9 (Tue",
    "image": "https://static.kivo.wiki/images/timeline/AZZ39XroTgiW7vlvfyfHRs8bLwNR27TH.jpg",
    "body": "[Unique Rerun Pick-Up Recruitment Preview]\n\nA Unique Rerun Pick-Up Recruitment will begin on 7/9 (Tue)!\nPick-Up Student: 3★ Mutsuki (New Year)\n\nPick-Up Recruitment Schedule:\n7/9 (Tue) After Maintenance – 7/16 (Tue) 1:59 AM (UTC)\n\n#BlueArchive\n![RnGPBwj19ziQhXFhjP1WoEn6NsIE8H1M.jpg](https://kivo.wiki/files/1348/RnGPBwj19ziQhXFhjP1WoEn6NsIE8H1M.jpg)",
    "type": "Gacha",
    "url": "twitter.com/EN_BlueArchive/status/1809108699442786730",
    "start_time": 1720519228,
    "end_time": 1721095228,
    "created_at": 1720624169,
    "updated_at": 1720624425
  },
  "message": "OK",
  "success": true,
  "time": 1780616965,
  "version": "1.0.0-beta.43"
}
