{
  "code": 2000,
  "codename": "Koyuki",
  "data": {
    "id": 3862,
    "line_type": "Globle",
    "title": "国际服活动「Balancing Schale's Books with the General Student Council」#9",
    "summary": "[Mini Event Notice] Hello. This is Blue Archive Team. Wait... It's not this.... sorry. let me try ag",
    "image": "https://static.kivo.wiki/images/timeline/66TJe9sC6cfP9jRgZRWSETQ6vNjZs2Bl.jpg",
    "body": "[Mini Event Notice]\n\nHello. This is Blue Archive Team.\nWait... It's not this.... sorry. let me try again. \nAhem...\n\nHello Sensei!\n\nBalancing Schale's Books with the General Student Council is back!\nEarn enhancement materials and a whole bunch of credits!\n\n🗓️Event Period:\n4/1 (Tue) After Maintenance - 4/15 (Tue) 1:59 AM (UTC)\n\n#BlueArchive\n![image.png](https://kivo.wiki/files/526/0USYCPv4CtarY22Grw3V6pXwToCq9Zn6.png)\n",
    "type": "Event",
    "url": "x.com/EN_BlueArchive/status/1906938324284997649",
    "start_time": 1743490800,
    "end_time": 1744682340,
    "created_at": 1744580051,
    "updated_at": 1754821763
  },
  "message": "OK",
  "success": true,
  "time": 1780616709,
  "version": "1.0.0-beta.43"
}
