{
  "code": 2000,
  "codename": "Koyuki",
  "data": {
    "id": 4354,
    "line_type": "Globle",
    "title": "国际服炸服 #24",
    "summary": "[8/7(Thu) Temporary Maintenance Notice] There is temporary maintenance scheduled today on 8/7(Thu). ",
    "image": "https://static.kivo.wiki/images/timeline/y5Cqjz9aL9it98DqSBnZ558L5C92F5Qm.jpg",
    "body": "[8/7(Thu) Temporary Maintenance Notice]\n\nThere is temporary maintenance scheduled today on 8/7(Thu).\nPlease note that the game will be unavailable during this time.\n\n🗓️Maintenance Period:  8/7(Thu) 6:00 AM – 7:00 AM(UTC)\n➡️Details: https://forum.nexon.com/bluearchive-en/board_view?board=3217&thread=3081297\n\n※ Maintenance times may change based on conditions.\n#BlueArchive\n\n![GxkyFUtaoAAY1DF.jpg](https://kivo.wiki/files/443/l2IR0Uue6e9w7mNMAPtcomYsoBD2r21s.jpg)\n",
    "type": "Maintenance",
    "url": "x.com/EN_BlueArchive/status/1953321966921986152",
    "start_time": 1754546400,
    "end_time": 1754550000,
    "created_at": 1754819870,
    "updated_at": 1759934644
  },
  "message": "OK",
  "success": true,
  "time": 1780616581,
  "version": "1.0.0-beta.43"
}
