{
  "code": 2000,
  "codename": "Koyuki",
  "data": {
    "id": 4448,
    "line_type": "Globle",
    "title": "8/31紧急维护后处理事项详细说明",
    "summary": "大家好，這裡是《蔚藍檔案》營運團隊。 首先，對於 8 月 31 日 (日) 部分內容出現異常顯示，造成各位老師的不便，我們深感抱歉。 目前針對本次狀況的調查已進入尾聲，以下為詳細經過、採取的應對措施、",
    "image": "",
    "body": "大家好，這裡是《蔚藍檔案》營運團隊。\n\n \n\n首先，對於 8 月 31 日 (日) 部分內容出現異常顯示，造成各位老師的不便，我們深感抱歉。\n\n目前針對本次狀況的調查已進入尾聲，以下為詳細經過、採取的應對措施、防止類似事件再次發生的對策，以及道歉補償內容的說明。\n\n \n\n【問題概要】\n\n- 8 月 31 日 (日) 發現部分影響用戶端的環境設定遭到未經授權的變更。\n\n- 當日晚間 9 點 22 分至 9 月 1 日 (一) 凌晨 3 點 40 分間，我們進行了緊急維護，排查攻擊路徑並加強安全防護。\n\n \n\n【問題原因】\n\n-《蔚藍檔案》用戶端啟動時，會透過 CDN 進行版本管理與登入伺服器等環境設定的確認。\n\n- 雖然這些設定由與遊戲分離的內部服務生成與管理，但可透過特定方式從外部存取並操作。\n\n- 本次事件中，部分環境設定被變更為 IP 位址 45.94.31.77 (荷蘭)，導致異常顯示問題。\n\n \n\n【影響範圍】\n\n- 除特定商店／Teen 版本外，其他版本出現部分內容異常顯示。\n\n- 包含橫幅異常、咖啡廳中顯示「小雪」與「初音未來」角色，以及特定 YouTube 曝光等情況。\n\n- 經詳細調查確認，除上述異常顯示外，未發現其他異常。\n\n- 此環境設定僅影響用戶端的顯示內容。\n\n- 老師們的帳號、遊戲資料與付款資訊皆由獨立資料庫管理，並透過遊戲伺服器進行驗證，因此未受到影響。\n\n \n\n【處理措施】\n\n- 已將 CDN 環境設定恢復原狀，並封鎖可發布至 CDN 的路徑，改為僅限內部存取。\n\n- 限制環境設定權限，僅授權地點可存取，並導入雙重管控機制。\n\n- 已向韓國網際網路振興院 (KISA) 通報，並配合資安調查與攻擊者追查。\n\n \n\n【防止類似事件再發的對策】\n\n- 定期檢查服務存取狀況，防止外部操控環境設定。\n\n- 強化環境設定變更前後的驗證流程。\n\n- 除現行安全漏洞診斷外，將針對用戶端、伺服器與相關服務進行更高強度的安全檢測，包括模擬駭客與 Bug Bounty 等。\n\n \n\n【道歉補償說明】\n\n對於本次事件造成老師們的擔憂與不便，我們深表歉意，並準備了以下補償內容。\n煩請各位老師於補償發送期間內登入遊戲並透過信箱領取。\n\n \n\n■ 補償對象：所有老師\n■ 補償內容：\n\n- 10 次招募票券 ×1\n\n- AP ×500\n\n- 戰術大賽硬幣 ×150\n\n- 精通證書 ×3,000\n\n- 信用貨幣 ×300,000\n\n- 課程表票券 ×7\n\n- 懸賞通緝票券 ×7\n\n- 學園交流會票券 ×7\n\n■ 發送時間：9 月 1 日（一）晚間 11 點 ～ 9 月 8 日（一）晚間 10 點 59 分止\n\n(郵件保管期限為 7 天，每帳號限領一次)\n\n \n\n※ 有關購買「每月青輝石組合包」、「半月青輝石組合包」、「2 週 AP 組合包」的老師們之未領取補償，將於後續公告中另行說明。\n\n \n\n我們將持續努力，致力於提供安全穩定的遊戲環境，敬請各位老師安心使用。",
    "type": "Other",
    "url": "forum.nexon.com/bluearchiveTW/board_view?board=3359&thread=3123140",
    "start_time": 1756738800,
    "end_time": 1756738800,
    "created_at": 1757053961,
    "updated_at": 1757053961
  },
  "message": "OK",
  "success": true,
  "time": 1780616559,
  "version": "1.0.0-beta.43"
}
