{
  "code": 2000,
  "codename": "Koyuki",
  "data": {
    "id": 4850,
    "line_type": "CN",
    "title": "悬赏通缉2倍 #33 & 日程2倍 #33",
    "summary": "“欢迎连接【什亭之箱】，老师。” 【掉落量2倍活动】即将开启！请不要错过哦！ 【悬赏通缉、日程】道具掉落量2倍 ■ 活动时间 12月11日 04:00 ~ 12月18日 03:59",
    "image": "https://static.kivo.wiki/images/timeline/5UI1f4HBdwo8Cwy0dzinoFzp3rr031mp.jpg",
    "body": "“欢迎连接【什亭之箱】，老师。”\n【掉落量2倍活动】即将开启！请不要错过哦！\n\n【悬赏通缉、日程】道具掉落量2倍\n■ 活动时间\n12月11日 04:00 ~ 12月18日 03:59",
    "type": "Double",
    "url": "bluearchive-cn.com/news/1611",
    "start_time": 1765431408,
    "end_time": 1766036208,
    "created_at": 1766381872,
    "updated_at": 1777272737
  },
  "message": "OK",
  "success": true,
  "time": 1780616480,
  "version": "1.0.0-beta.43"
}
