{
  "code": 2000,
  "codename": "Koyuki",
  "data": {
    "id": 4990,
    "line_type": "CN",
    "title": "学院交流会3倍 #12",
    "summary": "【悬赏通缉、学院交流会】道具掉落量3倍 ■ 活动时间 01月29日 维护结束后 ~ 02月05日 03:59",
    "image": "https://static.kivo.wiki/images/timeline/IikemMd765530lb6YbRFGB0Ob3S1TJJM.jpg",
    "body": "【悬赏通缉、学院交流会】道具掉落量3倍\n\n\n■ 活动时间\n\n\n01月29日 维护结束后 ~ 02月05日 03:59\n![image.png](https://kivo.wiki/files/2824/E0ZnUAluIUdXoNsi70Kpm52x33NEJ89F.png)\n",
    "type": "Double",
    "url": "bluearchive-cn.com/news/1668",
    "start_time": 1769697788,
    "end_time": 1770302588,
    "created_at": 1769438671,
    "updated_at": 1769441261
  },
  "message": "OK",
  "success": true,
  "time": 1780616424,
  "version": "1.0.0-beta.43"
}
