{
  "code": 2000,
  "codename": "Koyuki",
  "data": {
    "id": 552,
    "line_type": "JP",
    "title": "4th PV公开",
    "summary": "【4thPV公開】 先ほど #ブルアカらいぶ2周年SP ご覧いただいた『ブルーアーカイブ』の新しいPVが公開されました！ 先生… これから起こる事から… 目を、そらさないでください。 YouTube版",
    "image": "",
    "body": "【4thPV公開】\n先ほど #ブルアカらいぶ2周年SP ご覧いただいた『ブルーアーカイブ』の新しいPVが公開されました！\n\n先生…\nこれから起こる事から…\n目を、そらさないでください。\n\nYouTube版はこちらから\n[https://youtu.be/4rDOsvzTicY](http://)\n\n#ブルアカ\n#ブルアカ2周年\n#ブルアカふぇす",
    "type": "OutsideGames",
    "url": "twitter.com/Blue_ArchiveJP/status/1617101346410483713",
    "start_time": 1674385560,
    "end_time": 1674385560,
    "created_at": 1699061962,
    "updated_at": 1699061962
  },
  "message": "OK",
  "success": true,
  "time": 1780617393,
  "version": "1.0.0-beta.43"
}
