{
  "code": 2000,
  "codename": "Koyuki",
  "data": {
    "id": 744,
    "line_type": "JP",
    "title": "老师经验2倍集中通知 23-07-28",
    "summary": "【キャンペーン予告】 明日7/29(土)から8/21(月)までの間、「先生レベル経験値2倍キャンペーン」が全4回の日程で開催されます！ 効率良く先生のレベルを上げることができますので、スケジュールをご",
    "image": "https://static.kivo.wiki/images/timeline/rqffeOxEtOVdX3zkmSi0QHAaN63lxJxV.jpg",
    "body": "【キャンペーン予告】\n明日7/29(土)から8/21(月)までの間、「先生レベル経験値2倍キャンペーン」が全4回の日程で開催されます！\n効率良く先生のレベルを上げることができますので、スケジュールをご確認の上、ぜひご活用ください！\n※開催期間中、「熟達証書」の獲得量は2倍にはなりません。\n#ブルアカ\n![c3teBSuUJAOIfUJuv4XogLITmVu8wS39.jpg](https://kivo.wiki/files/153/c3teBSuUJAOIfUJuv4XogLITmVu8wS39.jpg)",
    "type": "Double",
    "url": "twitter.com/Blue_ArchiveJP/status/1684866421552230400",
    "start_time": 1690574400,
    "end_time": 1692561599,
    "created_at": 1699186240,
    "updated_at": 1777268309
  },
  "message": "OK",
  "success": true,
  "time": 1780617286,
  "version": "1.0.0-beta.43"
}
