{
  "code": 2000,
  "codename": "Koyuki",
  "data": {
    "id": 602,
    "title": "괜찮아, 지금 이대로 / It Will Be Alright",
    "cover": "https://static.kivo.wiki/images/music/cover/JOEr9bCO9hkFIxuCwVPPQQP9GdoDCl7i.png",
    "author": "尾刃叶渚 (CV: Kim Hyunsim), NECORD, Z:U",
    "album": "It Will Be Alright - Memories in Melody ",
    "use": "专辑曲目",
    "original_file_name": "",
    "introduction": "![already_staff.png](https://kivo.wiki/files/1348/L39yMAxlr4SRIDjtEMVBMkVsW9JWEKIk.png)\n",
    "file": "https://static.kivo.wiki/musics/01%20It%20Will%20Be%20Alright.m4a",
    "lrc_file": ""
  },
  "message": "请求成功",
  "success": true,
  "time": 1781470919,
  "version": "1.0.0-beta.43"
}
