{
  "code": 2000,
  "codename": "Koyuki",
  "data": {
    "id": 1159,
    "type": "furniture",
    "icon": "https://static.kivo.wiki/images/item/icon/UcsoT5EGm8Z2OvSX2ZpiwJyIrEUZhuy8.png",
    "rarity": 2,
    "name": "阳光阿罗哈壁挂",
    "description": "华丽的粉色花朵流水般从壁挂上垂下。散发着甜美的香气。",
    "article_id": 0,
    "gift": {
      "students": null
    },
    "furniture": {
      "comfort": 50,
      "students": null
    }
  },
  "message": "OK",
  "success": true,
  "time": 1781211630,
  "version": "1.0.0-beta.43"
}
