{
  "code": 2000,
  "codename": "Koyuki",
  "data": {
    "id": 1244,
    "type": "furniture",
    "icon": "https://static.kivo.wiki/images/item/icon/AxNxDs6S4cV5LRElpZs77NJI15WzjrDE.png",
    "rarity": 2,
    "name": "书法家书桌",
    "description": "坐在这美丽的书桌前，也许你也能写下名笔！？",
    "article_id": 0,
    "gift": {
      "students": null
    },
    "furniture": {
      "comfort": 50,
      "students": null
    }
  },
  "message": "OK",
  "success": true,
  "time": 1781297341,
  "version": "1.0.0-beta.43"
}
