{
  "code": 2000,
  "codename": "Koyuki",
  "data": {
    "id": 1272,
    "type": "furniture",
    "icon": "https://static.kivo.wiki/images/item/icon/OLjC80NWlF1aHXEvbQxz0Ya5GTQnuAXS.png",
    "rarity": 4,
    "name": "网状吊床",
    "description": "用渔村常见的网和钢条制成的简易吊床。虽然看上去不怎么样，但躺上去堪比高级床铺。",
    "article_id": 0,
    "gift": {
      "students": null
    },
    "furniture": {
      "comfort": 350,
      "students": [
        {
          "id": 286,
          "skin": "泳装",
          "family_name": "风仓",
          "given_name": "萌绘",
          "avatar": "https://static.kivo.wiki/images/students/%E9%A3%8E%E4%BB%93%20%E8%90%8C%E7%BB%98/%E6%B3%B3%E8%A3%85/avatar.png"
        }
      ]
    }
  },
  "message": "OK",
  "success": true,
  "time": 1780615160,
  "version": "1.0.0-beta.43"
}
