{
  "code": 2000,
  "codename": "Koyuki",
  "data": {
    "id": 1287,
    "type": "furniture",
    "icon": "https://static.kivo.wiki/images/item/icon/2CSwX9yCTHNWppGnJyhcdP1Hi1M4exVV.png",
    "rarity": 2,
    "name": "白色海滩躺椅",
    "description": "享受日光浴的理想海滩躺椅。为了便于随时跳入海中，还配备了泳圈。",
    "article_id": 0,
    "gift": {
      "students": null
    },
    "furniture": {
      "comfort": 50,
      "students": null
    }
  },
  "message": "OK",
  "success": true,
  "time": 1781296748,
  "version": "1.0.0-beta.43"
}
