{
  "code": 2000,
  "codename": "Koyuki",
  "data": {
    "id": 1402,
    "type": "default",
    "icon": "https://static.kivo.wiki/images/item/icon/5g22YHOwQ39re3wbSuMF3e9L1iwttlEa.png",
    "rarity": 4,
    "name": "正月系列家具选择箱",
    "description": "从正月系列家具中任意选择一个家具兑换的选择箱。",
    "article_id": 0,
    "gift": {
      "students": null
    },
    "furniture": {
      "comfort": 0,
      "students": null
    }
  },
  "message": "OK",
  "success": true,
  "time": 1781037482,
  "version": "1.0.0-beta.43"
}
