{
  "code": 2000,
  "codename": "Koyuki",
  "data": {
    "id": 1905,
    "type": "furniture",
    "icon": "https://static.kivo.wiki/images/item/icon/aw4Gs67IUUFC27kQ3RjRxcdUs9oJ4tXi.png",
    "rarity": 4,
    "name": "游戏开发部的日常",
    "description": "游戏开发部日常的片段。<br>对某些人来说的日常，也许正是闪闪发光的非日常。",
    "article_id": 0,
    "gift": {
      "students": null
    },
    "furniture": {
      "comfort": 350,
      "students": null
    }
  },
  "message": "OK",
  "success": true,
  "time": 1781038745,
  "version": "1.0.0-beta.43"
}
