{
  "code": 2000,
  "codename": "Koyuki",
  "data": {
    "id": 20,
    "type": "default",
    "icon": "https://static.kivo.wiki/images/item/icon/f5F5AoXH2hUzeK5jfRiL1vMXJ8nj2XhE.png",
    "rarity": 1,
    "name": "草莓巧克力蛋糕",
    "description": "和纱买来的草莓巧克力蛋糕。看样子是在甜品店的橱柜前纠结了很久才决定的。",
    "article_id": 0,
    "gift": {
      "students": null
    },
    "furniture": {
      "comfort": 0,
      "students": null
    }
  },
  "message": "OK",
  "success": true,
  "time": 1780774822,
  "version": "1.0.0-beta.43"
}
