{
  "code": 2000,
  "codename": "Koyuki",
  "data": {
    "id": 947,
    "type": "furniture",
    "icon": "https://static.kivo.wiki/images/item/icon/nS2hpfciE2eX3KhrW1XjT6IvhnSXjbra.png",
    "rarity": 2,
    "name": "情人节饼干沙发",
    "description": "饼干抱枕为亮点所在的情人节沙发。独特的设计增添甜美氛围。",
    "article_id": 0,
    "gift": {
      "students": null
    },
    "furniture": {
      "comfort": 50,
      "students": [
        {
          "id": 11,
          "skin": "",
          "family_name": "狐坂",
          "given_name": "若藻",
          "avatar": "https://static.kivo.wiki/images/students/%E7%8B%90%E5%9D%82%E8%8B%A5%E8%97%BB/avatar.png"
        }
      ]
    }
  },
  "message": "OK",
  "success": true,
  "time": 1781297266,
  "version": "1.0.0-beta.43"
}
